[{"currentLatency":0.956,"currentBuffer":0.966,"currentAverageThroughput":3844.5,"currentStallDuration":0,"currentQuality":null},{"currentLatency":0.956,"currentBuffer":0.843,"currentAverageThroughput":4055.25,"currentStallDuration":0,"currentQuality":null},{"currentLatency":0.956,"currentBuffer":0.851,"currentAverageThroughput":4055.25,"currentStallDuration":0,"currentQuality":null},{"currentLatency":0.956,"currentBuffer":0.951,"currentAverageThroughput":4415.285714285715,"currentStallDuration":0,"currentQuality":null},{"currentLatency":0.956,"currentBuffer":0.8,"currentAverageThroughput":4415.285714285715,"currentStallDuration":0,"currentQuality":null},{"currentLatency":0.956,"currentBuffer":0.88,"currentAverageThroughput":4415.285714285715,"currentStallDuration":0,"currentQuality":null},{"currentLatency":0.956,"currentBuffer":0.793,"currentAverageThroughput":5507.75,"currentStallDuration":0,"currentQuality":null},{"currentLatency":0.955,"currentBuffer":0.785,"currentAverageThroughput":5507.75,"currentStallDuration":0,"currentQuality":null},{"currentLatency":0.956,"currentBuffer":0.907,"currentAverageThroughput":5463.666666666667,"currentStallDuration":0,"currentQuality":null},{"currentLatency":0.955,"currentBuffer":0.893,"currentAverageThroughput":5463.666666666667,"currentStallDuration":0,"currentQuality":null},{"currentLatency":0.955,"currentBuffer":0.955,"currentAverageThroughput":5463.666666666667,"currentStallDuration":0,"currentQuality":null},{"currentLatency":0.955,"currentBuffer":0.869,"currentAverageThroughput":6108.5,"currentStallDuration":0,"currentQuality":null},{"currentLatency":0.956,"currentBuffer":0.785,"currentAverageThroughput":6108.5,"currentStallDuration":0,"currentQuality":null},{"currentLatency":0.955,"currentBuffer":0.893,"currentAverageThroughput":5853,"currentStallDuration":0,"currentQuality":null},{"currentLatency":0.956,"currentBuffer":0.911,"currentAverageThroughput":5853,"currentStallDuration":0,"currentQuality":null},{"currentLatency":0.956,"currentBuffer":0.95,"currentAverageThroughput":5853,"currentStallDuration":0,"currentQuality":null},{"currentLatency":0.956,"currentBuffer":0.867,"currentAverageThroughput":6178.857142857143,"currentStallDuration":0,"currentQuality":null},{"currentLatency":0.956,"currentBuffer":0.752,"currentAverageThroughput":6178.857142857143,"currentStallDuration":0,"currentQuality":null},{"currentLatency":0.956,"currentBuffer":0.925,"currentAverageThroughput":7040.625,"currentStallDuration":0,"currentQuality":null},{"currentLatency":0.956,"currentBuffer":0.843,"currentAverageThroughput":7040.625,"currentStallDuration":0,"currentQuality":null},{"currentLatency":0.956,"currentBuffer":0.655,"currentAverageThroughput":7040.625,"currentStallDuration":0,"currentQuality":null},{"currentLatency":0.956,"currentBuffer":0.82,"currentAverageThroughput":6393.333333333333,"currentStallDuration":0,"currentQuality":null},{"currentLatency":0.956,"currentBuffer":0.882,"currentAverageThroughput":6393.333333333333,"currentStallDuration":0,"currentQuality":null},{"currentLatency":0.956,"currentBuffer":0.938,"currentAverageThroughput":6053.9,"currentStallDuration":0,"currentQuality":null},{"currentLatency":0.956,"currentBuffer":0.792,"currentAverageThroughput":6053.9,"currentStallDuration":0,"currentQuality":null},{"currentLatency":0.956,"currentBuffer":0.948,"currentAverageThroughput":6053.9,"currentStallDuration":0,"currentQuality":null},{"currentLatency":0.956,"currentBuffer":0.869,"currentAverageThroughput":5270.375,"currentStallDuration":0,"currentQuality":null},{"currentLatency":0.956,"currentBuffer":0.891,"currentAverageThroughput":5270.375,"currentStallDuration":0,"currentQuality":null},{"currentLatency":0.956,"currentBuffer":0.93,"currentAverageThroughput":5566.666666666667,"currentStallDuration":0,"currentQuality":null},{"currentLatency":0.956,"currentBuffer":0.744,"currentAverageThroughput":5566.666666666667,"currentStallDuration":0,"currentQuality":null},{"currentLatency":0.956,"currentBuffer":0.89,"currentAverageThroughput":5566.666666666667,"currentStallDuration":0,"currentQuality":null},{"currentLatency":0.955,"currentBuffer":0.866,"currentAverageThroughput":6262.5,"currentStallDuration":0,"currentQuality":null},{"currentLatency":0.956,"currentBuffer":0.749,"currentAverageThroughput":6262.5,"currentStallDuration":0,"currentQuality":null},{"currentLatency":0.956,"currentBuffer":0.928,"currentAverageThroughput":5995.545454545455,"currentStallDuration":0,"currentQuality":null},{"currentLatency":0.956,"currentBuffer":0.693,"currentAverageThroughput":5995.545454545455,"currentStallDuration":0,"currentQuality":null},{"currentLatency":0.956,"currentBuffer":0.878,"currentAverageThroughput":5995.545454545455,"currentStallDuration":0,"currentQuality":null},{"currentLatency":0.956,"currentBuffer":0.864,"currentAverageThroughput":6192,"currentStallDuration":0,"currentQuality":null},{"currentLatency":0.956,"currentBuffer":0.944,"currentAverageThroughput":6192,"currentStallDuration":0,"currentQuality":null},{"currentLatency":0.956,"currentBuffer":0.95,"currentAverageThroughput":6037.076923076923,"currentStallDuration":0,"currentQuality":null},{"currentLatency":0.956,"currentBuffer":0.807,"currentAverageThroughput":6037.076923076923,"currentStallDuration":0,"currentQuality":null},{"currentLatency":0.956,"currentBuffer":0.857,"currentAverageThroughput":6037.076923076923,"currentStallDuration":0,"currentQuality":null},{"currentLatency":0.956,"currentBuffer":0.911,"currentAverageThroughput":6150.428571428572,"currentStallDuration":0,"currentQuality":null},{"currentLatency":0.956,"currentBuffer":0.945,"currentAverageThroughput":6150.428571428572,"currentStallDuration":0,"currentQuality":null},{"currentLatency":0.956,"currentBuffer":0.942,"currentAverageThroughput":6239.357142857143,"currentStallDuration":0,"currentQuality":null},{"currentLatency":0.956,"currentBuffer":0.822,"currentAverageThroughput":6239.357142857143,"currentStallDuration":0,"currentQuality":null},{"currentLatency":0.956,"currentBuffer":0.953,"currentAverageThroughput":6239.357142857143,"currentStallDuration":0,"currentQuality":null},{"currentLatency":0.956,"currentBuffer":0.865,"currentAverageThroughput":6108.533333333334,"currentStallDuration":0,"currentQuality":null},{"currentLatency":0.956,"currentBuffer":0.872,"currentAverageThroughput":6108.533333333334,"currentStallDuration":0,"currentQuality":null},{"currentLatency":0.956,"currentBuffer":0.889,"currentAverageThroughput":6172.8125,"currentStallDuration":0,"currentQuality":null},{"currentLatency":0.956,"currentBuffer":0.813,"currentAverageThroughput":6172.8125,"currentStallDuration":0,"currentQuality":null},{"currentLatency":0.956,"currentBuffer":0.713,"currentAverageThroughput":6172.8125,"currentStallDuration":0,"currentQuality":null},{"currentLatency":0.956,"currentBuffer":0.599,"currentAverageThroughput":6172.8125,"currentStallDuration":0,"currentQuality":null},{"currentLatency":0.956,"currentBuffer":0.351,"currentAverageThroughput":6172.8125,"currentStallDuration":0,"currentQuality":null},{"currentLatency":0.956,"currentBuffer":0.351,"currentAverageThroughput":6172.8125,"currentStallDuration":0,"currentQuality":null},{"currentLatency":0.956,"currentBuffer":0.197,"currentAverageThroughput":5894.941176470588,"currentStallDuration":0,"currentQuality":null},{"currentLatency":0.981,"currentBuffer":0.001,"currentAverageThroughput":5894.941176470588,"currentStallDuration":0,"currentQuality":null},{"currentLatency":1.182,"currentBuffer":0.001,"currentAverageThroughput":5894.941176470588,"currentStallDuration":0,"currentQuality":null},{"currentLatency":1.381,"currentBuffer":0.001,"currentAverageThroughput":5894.941176470588,"currentStallDuration":0,"currentQuality":null},{"currentLatency":1.582,"currentBuffer":0.001,"currentAverageThroughput":5894.941176470588,"currentStallDuration":0,"currentQuality":null},{"currentLatency":1.781,"currentBuffer":0.001,"currentAverageThroughput":5894.941176470588,"currentStallDuration":0,"currentQuality":null},{"currentLatency":1.982,"currentBuffer":0.001,"currentAverageThroughput":5894.941176470588,"currentStallDuration":0,"currentQuality":null},{"currentLatency":2.182,"currentBuffer":0.001,"currentAverageThroughput":5894.941176470588,"currentStallDuration":0,"currentQuality":null},{"currentLatency":2.285,"currentBuffer":0.419,"currentAverageThroughput":5584.277777777777,"currentStallDuration":1503.759999992326,"currentQuality":null},{"currentLatency":2.286,"currentBuffer":0.326,"currentAverageThroughput":5584.277777777777,"currentStallDuration":0,"currentQuality":null},{"currentLatency":2.312,"currentBuffer":0.032,"currentAverageThroughput":5584.277777777777,"currentStallDuration":0,"currentQuality":null},{"currentLatency":2.513,"currentBuffer":0.032,"currentAverageThroughput":5584.277777777777,"currentStallDuration":0,"currentQuality":null},{"currentLatency":2.712,"currentBuffer":0.032,"currentAverageThroughput":5584.277777777777,"currentStallDuration":0,"currentQuality":null},{"currentLatency":2.912,"currentBuffer":0.032,"currentAverageThroughput":5584.277777777777,"currentStallDuration":0,"currentQuality":null},{"currentLatency":3.112,"currentBuffer":0.032,"currentAverageThroughput":5584.277777777777,"currentStallDuration":0,"currentQuality":null},{"currentLatency":3.312,"currentBuffer":0.032,"currentAverageThroughput":5584.277777777777,"currentStallDuration":0,"currentQuality":null},{"currentLatency":3.339,"currentBuffer":0.532,"currentAverageThroughput":5584.277777777777,"currentStallDuration":1250.4300000000512,"currentQuality":null},{"currentLatency":3.339,"currentBuffer":0.226,"currentAverageThroughput":5584.277777777777,"currentStallDuration":0,"currentQuality":null},{"currentLatency":3.417,"currentBuffer":0.035,"currentAverageThroughput":5584.277777777777,"currentStallDuration":0,"currentQuality":null},{"currentLatency":3.615,"currentBuffer":0.035,"currentAverageThroughput":5584.277777777777,"currentStallDuration":0,"currentQuality":null},{"currentLatency":3.816,"currentBuffer":0.035,"currentAverageThroughput":5584.277777777777,"currentStallDuration":0,"currentQuality":null},{"currentLatency":4.015,"currentBuffer":0.035,"currentAverageThroughput":5584.277777777777,"currentStallDuration":0,"currentQuality":null},{"currentLatency":4.215,"currentBuffer":0.035,"currentAverageThroughput":5584.277777777777,"currentStallDuration":0,"currentQuality":null},{"currentLatency":4.404,"currentBuffer":0.535,"currentAverageThroughput":5584.277777777777,"currentStallDuration":1253.1550000130665,"currentQuality":null},{"currentLatency":4.405,"currentBuffer":0.347,"currentAverageThroughput":5584.277777777777,"currentStallDuration":0,"currentQuality":null},{"currentLatency":4.405,"currentBuffer":0.347,"currentAverageThroughput":5584.277777777777,"currentStallDuration":0,"currentQuality":null},{"currentLatency":4.516,"currentBuffer":0.035,"currentAverageThroughput":5584.277777777777,"currentStallDuration":0,"currentQuality":null},{"currentLatency":4.715,"currentBuffer":0.035,"currentAverageThroughput":5584.277777777777,"currentStallDuration":0,"currentQuality":null},{"currentLatency":4.917,"currentBuffer":0.035,"currentAverageThroughput":5584.277777777777,"currentStallDuration":0,"currentQuality":null},{"currentLatency":5.117,"currentBuffer":0.035,"currentAverageThroughput":5584.277777777777,"currentStallDuration":0,"currentQuality":null},{"currentLatency":5.315,"currentBuffer":0.035,"currentAverageThroughput":5584.277777777777,"currentStallDuration":0,"currentQuality":null},{"currentLatency":5.516,"currentBuffer":0.035,"currentAverageThroughput":5584.277777777777,"currentStallDuration":1252.1750000014435,"currentQuality":null},{"currentLatency":5.627,"currentBuffer":0.46,"currentAverageThroughput":5026.571428571428,"currentStallDuration":0,"currentQuality":null},{"currentLatency":5.627,"currentBuffer":0.255,"currentAverageThroughput":5026.571428571428,"currentStallDuration":0,"currentQuality":null},{"currentLatency":5.627,"currentBuffer":0.255,"currentAverageThroughput":5026.571428571428,"currentStallDuration":0,"currentQuality":null},{"currentLatency":5.736,"currentBuffer":0.538,"currentAverageThroughput":5026.571428571428,"currentStallDuration":254.92000000667758,"currentQuality":{"mediaType":"video","bitrate":200000,"width":640,"height":360,"scanType":null,"qualityIndex":0}},{"currentLatency":5.735,"currentBuffer":0.272,"currentAverageThroughput":5026.571428571428,"currentStallDuration":0,"currentQuality":null},{"currentLatency":5.735,"currentBuffer":0.646,"currentAverageThroughput":5026.571428571428,"currentStallDuration":0,"currentQuality":null},{"currentLatency":5.735,"currentBuffer":0.396,"currentAverageThroughput":5026.571428571428,"currentStallDuration":0,"currentQuality":null},{"currentLatency":5.735,"currentBuffer":0.396,"currentAverageThroughput":5026.571428571428,"currentStallDuration":0,"currentQuality":null},{"currentLatency":5.829,"currentBuffer":0.048,"currentAverageThroughput":5026.571428571428,"currentStallDuration":249.6850000025006,"currentQuality":null},{"currentLatency":5.893,"currentBuffer":0.456,"currentAverageThroughput":5026.571428571428,"currentStallDuration":0,"currentQuality":null},{"currentLatency":5.894,"currentBuffer":0.381,"currentAverageThroughput":5026.571428571428,"currentStallDuration":0,"currentQuality":null},{"currentLatency":5.894,"currentBuffer":0.527,"currentAverageThroughput":5026.571428571428,"currentStallDuration":0,"currentQuality":null},{"currentLatency":5.893,"currentBuffer":0.455,"currentAverageThroughput":5026.571428571428,"currentStallDuration":0,"currentQuality":null},{"currentLatency":5.893,"currentBuffer":0.119,"currentAverageThroughput":5026.571428571428,"currentStallDuration":0,"currentQuality":null},{"currentLatency":5.925,"currentBuffer":0.535,"currentAverageThroughput":5026.571428571428,"currentStallDuration":250.72999999974854,"currentQuality":null},{"currentLatency":5.925,"currentBuffer":0.788,"currentAverageThroughput":5026.571428571428,"currentStallDuration":0,"currentQuality":null},{"currentLatency":5.925,"currentBuffer":0.561,"currentAverageThroughput":5026.571428571428,"currentStallDuration":0,"currentQuality":null},{"currentLatency":5.924,"currentBuffer":0.509,"currentAverageThroughput":5026.571428571428,"currentStallDuration":0,"currentQuality":null},{"currentLatency":5.924,"currentBuffer":0.661,"currentAverageThroughput":5026.571428571428,"currentStallDuration":0,"currentQuality":null},{"currentLatency":5.925,"currentBuffer":0.564,"currentAverageThroughput":5026.571428571428,"currentStallDuration":0,"currentQuality":null},{"currentLatency":5.924,"currentBuffer":0.315,"currentAverageThroughput":5026.571428571428,"currentStallDuration":0,"currentQuality":null},{"currentLatency":5.924,"currentBuffer":0.062,"currentAverageThroughput":5026.571428571428,"currentStallDuration":0,"currentQuality":null},{"currentLatency":5.925,"currentBuffer":0.881,"currentAverageThroughput":4738.466666666666,"currentStallDuration":0,"currentQuality":null},{"currentLatency":5.924,"currentBuffer":0.814,"currentAverageThroughput":4738.466666666666,"currentStallDuration":0,"currentQuality":null},{"currentLatency":5.924,"currentBuffer":0.564,"currentAverageThroughput":4738.466666666666,"currentStallDuration":0,"currentQuality":null},{"currentLatency":5.924,"currentBuffer":0.314,"currentAverageThroughput":4738.466666666666,"currentStallDuration":0,"currentQuality":null},{"currentLatency":5.924,"currentBuffer":0.564,"currentAverageThroughput":3218.222222222222,"currentStallDuration":0,"currentQuality":null},{"currentLatency":5.924,"currentBuffer":0.412,"currentAverageThroughput":3218.222222222222,"currentStallDuration":0,"currentQuality":null},{"currentLatency":5.924,"currentBuffer":0.315,"currentAverageThroughput":3218.222222222222,"currentStallDuration":0,"currentQuality":null},{"currentLatency":5.924,"currentBuffer":0.945,"currentAverageThroughput":777.5,"currentStallDuration":0,"currentQuality":null},{"currentLatency":5.924,"currentBuffer":0.814,"currentAverageThroughput":777.5,"currentStallDuration":0,"currentQuality":null},{"currentLatency":5.924,"currentBuffer":0.563,"currentAverageThroughput":777.5,"currentStallDuration":0,"currentQuality":null},{"currentLatency":5.925,"currentBuffer":0.563,"currentAverageThroughput":777.5,"currentStallDuration":0,"currentQuality":null},{"currentLatency":5.924,"currentBuffer":0.799,"currentAverageThroughput":777.5,"currentStallDuration":0,"currentQuality":null},{"currentLatency":5.924,"currentBuffer":0.511,"currentAverageThroughput":777.5,"currentStallDuration":0,"currentQuality":null},{"currentLatency":5.925,"currentBuffer":0.315,"currentAverageThroughput":777.5,"currentStallDuration":0,"currentQuality":null},{"currentLatency":5.925,"currentBuffer":0.561,"currentAverageThroughput":805.5,"currentStallDuration":0,"currentQuality":null},{"currentLatency":5.924,"currentBuffer":0.561,"currentAverageThroughput":805.5,"currentStallDuration":0,"currentQuality":null},{"currentLatency":5.924,"currentBuffer":0.312,"currentAverageThroughput":805.5,"currentStallDuration":0,"currentQuality":null},{"currentLatency":5.967,"currentBuffer":0.503,"currentAverageThroughput":805.5,"currentStallDuration":251.38499999593478,"currentQuality":null},{"currentLatency":5.967,"currentBuffer":0.828,"currentAverageThroughput":805.5,"currentStallDuration":0,"currentQuality":null},{"currentLatency":5.967,"currentBuffer":0.654,"currentAverageThroughput":805.5,"currentStallDuration":0,"currentQuality":null},{"currentLatency":5.968,"currentBuffer":0.577,"currentAverageThroughput":805.5,"currentStallDuration":0,"currentQuality":null},{"currentLatency":5.967,"currentBuffer":0.735,"currentAverageThroughput":805.5,"currentStallDuration":0,"currentQuality":null},{"currentLatency":5.968,"currentBuffer":0.574,"currentAverageThroughput":805.5,"currentStallDuration":0,"currentQuality":null},{"currentLatency":5.968,"currentBuffer":0.326,"currentAverageThroughput":805.5,"currentStallDuration":0,"currentQuality":null},{"currentLatency":5.968,"currentBuffer":0.591,"currentAverageThroughput":805.5,"currentStallDuration":0,"currentQuality":null},{"currentLatency":5.968,"currentBuffer":0.945,"currentAverageThroughput":805.5,"currentStallDuration":0,"currentQuality":null},{"currentLatency":5.968,"currentBuffer":0.753,"currentAverageThroughput":805.5,"currentStallDuration":0,"currentQuality":null},{"currentLatency":5.967,"currentBuffer":0.577,"currentAverageThroughput":805.5,"currentStallDuration":0,"currentQuality":null},{"currentLatency":5.968,"currentBuffer":0.801,"currentAverageThroughput":812.25,"currentStallDuration":0,"currentQuality":null},{"currentLatency":5.968,"currentBuffer":0.801,"currentAverageThroughput":812.25,"currentStallDuration":0,"currentQuality":null},{"currentLatency":5.968,"currentBuffer":0.553,"currentAverageThroughput":812.25,"currentStallDuration":0,"currentQuality":null},{"currentLatency":5.967,"currentBuffer":0.329,"currentAverageThroughput":812.25,"currentStallDuration":0,"currentQuality":null},{"currentLatency":5.968,"currentBuffer":0.575,"currentAverageThroughput":812.25,"currentStallDuration":0,"currentQuality":null},{"currentLatency":5.968,"currentBuffer":0.329,"currentAverageThroughput":812.25,"currentStallDuration":0,"currentQuality":null},{"currentLatency":5.967,"currentBuffer":0.329,"currentAverageThroughput":812.25,"currentStallDuration":0,"currentQuality":null},{"currentLatency":6.011,"currentBuffer":0.547,"currentAverageThroughput":806,"currentStallDuration":251.7050000024028,"currentQuality":null},{"currentLatency":6.011,"currentBuffer":0.837,"currentAverageThroughput":806,"currentStallDuration":0,"currentQuality":null},{"currentLatency":6.011,"currentBuffer":0.59,"currentAverageThroughput":806,"currentStallDuration":0,"currentQuality":null},{"currentLatency":6.011,"currentBuffer":0.339,"currentAverageThroughput":806,"currentStallDuration":0,"currentQuality":null},{"currentLatency":6.011,"currentBuffer":0.747,"currentAverageThroughput":819.25,"currentStallDuration":0,"currentQuality":null},{"currentLatency":6.011,"currentBuffer":0.498,"currentAverageThroughput":819.25,"currentStallDuration":0,"currentQuality":null},{"currentLatency":6.011,"currentBuffer":0.239,"currentAverageThroughput":819.25,"currentStallDuration":0,"currentQuality":null}]